pyqode/core/__init__.py
pyqode/core/cache.py
pyqode/core/icons.py
pyqode/core/share.py
pyqode/core/_designer_plugins/__init__.py
pyqode/core/_designer_plugins/code_edit_plugin.py
pyqode/core/_designer_plugins/errors_table_plugin.py
pyqode/core/_designer_plugins/interactive_console_plugin.py
pyqode/core/_designer_plugins/tab_widget_plugin.py
pyqode/core/_forms/__init__.py
pyqode/core/_forms/dlg_encodings_ui.py
pyqode/core/_forms/dlg_goto_line_ui.py
pyqode/core/_forms/dlg_preferred_encodings_editor_ui.py
pyqode/core/_forms/dlg_unsaved_files_ui.py
pyqode/core/_forms/pnl_encoding_ui.py
pyqode/core/_forms/pnl_read_only_ui.py
pyqode/core/_forms/popup_open_files_ui.py
pyqode/core/_forms/pyqode_core_rc.py
pyqode/core/_forms/search_panel_ui.py
pyqode/core/api/__init__.py
pyqode/core/api/client.py
pyqode/core/api/code_edit.py
pyqode/core/api/decoration.py
pyqode/core/api/encodings.py
pyqode/core/api/folding.py
pyqode/core/api/manager.py
pyqode/core/api/mode.py
pyqode/core/api/panel.py
pyqode/core/api/syntax_highlighter.py
pyqode/core/api/utils.py
pyqode/core/backend/__init__.py
pyqode/core/backend/server.py
pyqode/core/backend/workers.py
pyqode/core/dialogs/__init__.py
pyqode/core/dialogs/encodings.py
pyqode/core/dialogs/goto.py
pyqode/core/dialogs/unsaved_files.py
pyqode/core/managers/__init__.py
pyqode/core/managers/backend.py
pyqode/core/managers/decorations.py
pyqode/core/managers/file.py
pyqode/core/managers/modes.py
pyqode/core/managers/panels.py
pyqode/core/modes/__init__.py
pyqode/core/modes/autocomplete.py
pyqode/core/modes/autoindent.py
pyqode/core/modes/backspace.py
pyqode/core/modes/breakpoint.py
pyqode/core/modes/calltips.py
pyqode/core/modes/caret_line_highlight.py
pyqode/core/modes/case_converter.py
pyqode/core/modes/checker.py
pyqode/core/modes/code_completion.py
pyqode/core/modes/comments.py
pyqode/core/modes/cursor_history.py
pyqode/core/modes/extended_selection.py
pyqode/core/modes/filewatcher.py
pyqode/core/modes/image_annotations.py
pyqode3_core-4.0.1.dist-info/LICENSE
pyqode3_core-4.0.1.dist-info/WHEEL
pyqode3_core-4.0.1.dist-info/METADATA
pyqode3_core-4.0.1.dist-info/RECORD
