Metadata-Version: 2.1
Name: pyqode3-core
Version: 4.0.1
Summary: The core package contains the core components needed for writing a pyqode based
Keywords: CodeEdit,PyQt,editor,widget,qt
Author-email: Colin Duquesnoy <colin.duquesnoy@gmail.com>, Sebastiaan Mathôt <s.mathot@cogsci.nl>
Requires-Python: >=3.7
Requires-Dist: future
Requires-Dist: qtawesome
Requires-Dist: pathspec
Project-URL: Documentation, https://github.com/open-cogsci/pyqode.core
Project-URL: Source, https://github.com/open-cogsci/pyqode.core
